Calc_toolkit/__init__.py
Calc_toolkit/calculator.py
calc_toolkit-0.1.0.dist-info/LICENSE
calc_toolkit-0.1.0.dist-info/METADATA
calc_toolkit-0.1.0.dist-info/WHEEL
calc_toolkit-0.1.0.dist-info/top_level.txt
calc_toolkit-0.1.0.dist-info/RECORD
