Metadata-Version: 2.1
Name: calc_toolkit
Version: 0.1.0
Summary: Calc toolkit package for basic geometric calculations
Home-page: https://github.com/Pankaj01111/calc_tootkit
Author: Pankaj Verma
Author-email: pankajver@gmail.com
Classifier: Programming Language :: Python :: 3
Classifier: License :: OSI Approved :: MIT License
Classifier: Operating System :: OS Independent
Requires-Python: >=3.6
License-File: LICENSE
